{
  "charmap_dialog-splitter-state": {
    "__class__": "bytearray",
    "__value__": "AAAA/wAAAAEAAAACAAABAAAAAQAA/////wEAAAABAA=="
  },
  "check-book-splitter-state": {
    "__class__": "bytearray",
    "__value__": "AAAA/wAAAAEAAAACAAAARgAAAEYA/////wEAAAABAA=="
  },
  "custom_colors_for_color_dialog": [
    [
      255,
      255,
      255,
      255
    ],
    [
      255,
      255,
      255,
      255
    ],
    [
      255,
      255,
      255,
      255
    ],
    [
      255,
      255,
      255,
      255
    ],
    [
      255,
      255,
      255,
      255
    ],
    [
      255,
      255,
      255,
      255
    ],
    [
      255,
      255,
      255,
      255
    ],
    [
      255,
      255,
      255,
      255
    ],
    [
      255,
      255,
      255,
      255
    ],
    [
      255,
      255,
      255,
      255
    ],
    [
      255,
      255,
      255,
      255
    ],
    [
      255,
      255,
      255,
      255
    ],
    [
      255,
      255,
      255,
      255
    ],
    [
      255,
      255,
      255,
      255
    ],
    [
      255,
      255,
      255,
      255
    ],
    [
      255,
      255,
      255,
      255
    ]
  ],
  "dock_bottom_left": null,
  "dock_bottom_right": null,
  "dock_top_left": null,
  "dock_top_right": null,
  "engine_preview_sans_family": "Nimbus Sans [UKWN]",
  "find-widget-state": {
    "case_sensitive": false,
    "direction": "down",
    "dot_all": false,
    "mode": "normal",
    "where": "current",
    "wrap": true
  },
  "geometry-of-charmap_dialog-geometry": {
    "frame_geometry": {
      "height": 620,
      "width": 804,
      "x": 795,
      "y": 162
    },
    "full_screened": false,
    "geometry": {
      "height": 600,
      "width": 800,
      "x": 797,
      "y": 180
    },
    "maximized": false,
    "normal_geometry": {
      "height": 600,
      "width": 800,
      "x": 797,
      "y": 180
    },
    "qt": {
      "__class__": "bytearray",
      "__value__": "AdnQywADAAAAAAMbAAAAogAABj4AAAMNAAADHQAAALQAAAY8AAADCwAAAAAAAAAABkAAAAMdAAAAtAAABjwAAAML"
    },
    "screen": {
      "depth": 24,
      "device_pixel_ratio": 1.0,
      "geometry_in_logical_pixels": {
        "height": 900,
        "width": 1600,
        "x": 0,
        "y": 0
      },
      "index_in_screens_list": 0,
      "manufacturer": "AU Optronics",
      "model": "",
      "name": "eDP-1",
      "serial": "",
      "size_in_logical_pixels": {
        "height": 900,
        "width": 1600
      },
      "virtual_geometry": {
        "height": 900,
        "width": 1600,
        "x": 0,
        "y": 0
      }
    }
  },
  "geometry-of-import-foreign-geometry": {
    "frame_geometry": {
      "height": 221,
      "width": 526,
      "x": 533,
      "y": 328
    },
    "full_screened": false,
    "geometry": {
      "height": 201,
      "width": 522,
      "x": 535,
      "y": 346
    },
    "maximized": false,
    "normal_geometry": {
      "height": 201,
      "width": 522,
      "x": 535,
      "y": 346
    },
    "qt": {
      "__class__": "bytearray",
      "__value__": "AdnQywADAAAAAAIVAAABSAAABCIAAAIkAAACFwAAAVoAAAQgAAACIgAAAAAAAAAABkAAAAIXAAABWgAABCAAAAIi"
    },
    "screen": {
      "depth": 24,
      "device_pixel_ratio": 1.0,
      "geometry_in_logical_pixels": {
        "height": 900,
        "width": 1600,
        "x": 0,
        "y": 0
      },
      "index_in_screens_list": 0,
      "manufacturer": "AU Optronics",
      "model": "",
      "name": "eDP-1",
      "serial": "",
      "size_in_logical_pixels": {
        "height": 900,
        "width": 1600
      },
      "virtual_geometry": {
        "height": 900,
        "width": 1600,
        "x": 0,
        "y": 0
      }
    }
  },
  "geometry-of-main_window_geometry": {
    "frame_geometry": {
      "height": 752,
      "width": 1128,
      "x": 0,
      "y": 0
    },
    "full_screened": true,
    "geometry": {
      "height": 752,
      "width": 1128,
      "x": 0,
      "y": 0
    },
    "maximized": true,
    "normal_geometry": {
      "height": 752,
      "width": 1128,
      "x": 0,
      "y": 0
    },
    "qt": {
      "__class__": "bytearray",
      "__value__": "AdnQywADAAAAAAAAAAAAAAAABGcAAALvAAAAAAAAAAAAAARnAAAC7wAAAAACBAAABGgAAAAAAAAAAAAABGcAAALv"
    },
    "screen": {
      "depth": 32,
      "device_pixel_ratio": 2.0,
      "geometry_in_logical_pixels": {
        "height": 752,
        "width": 1128,
        "x": 0,
        "y": 0
      },
      "index_in_screens_list": 0,
      "manufacturer": "BOE",
      "model": "0x0BCA",
      "name": "eDP-1",
      "serial": "",
      "size_in_logical_pixels": {
        "height": 752,
        "width": 1128
      },
      "virtual_geometry": {
        "height": 752,
        "width": 1128,
        "x": 0,
        "y": 0
      }
    }
  },
  "geometry-of-preferences_geom": {
    "frame_geometry": {
      "height": 620,
      "width": 916,
      "x": 688,
      "y": 180
    },
    "full_screened": false,
    "geometry": {
      "height": 600,
      "width": 912,
      "x": 690,
      "y": 198
    },
    "maximized": false,
    "normal_geometry": {
      "height": 600,
      "width": 912,
      "x": 690,
      "y": 198
    },
    "qt": {
      "__class__": "bytearray",
      "__value__": "AdnQywADAAAAAAKwAAAAtAAABkMAAAMfAAACsgAAAMYAAAZBAAADHQAAAAAAAAAABkAAAAKyAAAAxgAABkEAAAMd"
    },
    "screen": {
      "depth": 24,
      "device_pixel_ratio": 1.0,
      "geometry_in_logical_pixels": {
        "height": 900,
        "width": 1600,
        "x": 0,
        "y": 0
      },
      "index_in_screens_list": 0,
      "manufacturer": "AU Optronics",
      "model": "",
      "name": "eDP-1",
      "serial": "",
      "size_in_logical_pixels": {
        "height": 900,
        "width": 1600
      },
      "virtual_geometry": {
        "height": 900,
        "width": 1600,
        "x": 0,
        "y": 0
      }
    }
  },
  "geometry-of-reports-dialog-geometry": {
    "frame_geometry": {
      "height": 620,
      "width": 954,
      "x": 323,
      "y": 154
    },
    "full_screened": false,
    "geometry": {
      "height": 600,
      "width": 950,
      "x": 325,
      "y": 172
    },
    "maximized": false,
    "normal_geometry": {
      "height": 600,
      "width": 950,
      "x": 325,
      "y": 172
    },
    "qt": {
      "__class__": "bytearray",
      "__value__": "AdnQywADAAAAAAFDAAAAmgAABPwAAAMFAAABRQAAAKwAAAT6AAADAwAAAAAAAAAABkAAAAFFAAAArAAABPoAAAMD"
    },
    "screen": {
      "depth": 24,
      "device_pixel_ratio": 1.0,
      "geometry_in_logical_pixels": {
        "height": 900,
        "width": 1600,
        "x": 0,
        "y": 0
      },
      "index_in_screens_list": 0,
      "manufacturer": "AU Optronics",
      "model": "",
      "name": "eDP-1",
      "serial": "",
      "size_in_logical_pixels": {
        "height": 900,
        "width": 1600
      },
      "virtual_geometry": {
        "height": 900,
        "width": 1600,
        "x": 0,
        "y": 0
      }
    }
  },
  "geometry-of-toc_editor_window_geom": {
    "frame_geometry": {
      "height": 650,
      "width": 954,
      "x": 648,
      "y": 131
    },
    "full_screened": false,
    "geometry": {
      "height": 630,
      "width": 950,
      "x": 650,
      "y": 149
    },
    "maximized": false,
    "normal_geometry": {
      "height": 630,
      "width": 950,
      "x": 650,
      "y": 149
    },
    "qt": {
      "__class__": "bytearray",
      "__value__": "AdnQywADAAAAAAKIAAAAgwAABkEAAAMMAAACigAAAJUAAAY/AAADCgAAAAAAAAAABkAAAAKKAAAAlQAABj8AAAMK"
    },
    "screen": {
      "depth": 24,
      "device_pixel_ratio": 1.0,
      "geometry_in_logical_pixels": {
        "height": 900,
        "width": 1600,
        "x": 0,
        "y": 0
      },
      "index_in_screens_list": 0,
      "manufacturer": "AU Optronics",
      "model": "",
      "name": "eDP-1",
      "serial": "",
      "size_in_logical_pixels": {
        "height": 900,
        "width": 1600
      },
      "virtual_geometry": {
        "height": 900,
        "width": 1600,
        "x": 0,
        "y": 0
      }
    }
  },
  "html-editor-state": {
    "__class__": "bytearray",
    "__value__": "AAAA/wAAAAD9AAAAAAAAAL4AAALXAAAABAAAAAQAAAAIAAAACPwAAAABAAAAAgAAAAMAAAAUAGEAYwB0AGkAbwBuAF8AYgBhAHIBAAAAAP////8AAAAAAAAAAAAAABIAdABvAG8AbABzAF8AYgBhAHIBAAAAQv////8AAAAAAAAAAAAAAB4AaAB0AG0AbABfAGYAbwByAG0AYQB0AF8AYgBhAHIBAAAAgP////8AAAAAAAAAAA=="
  },
  "import-foreign-geometry": {
    "__class__": "bytearray",
    "__value__": "AdnQywADAAAAAAIRAAABNgAABB4AAAIAAAACEwAAATYAAAQcAAAB/gAAAAAAAAAABkAAAAITAAABNgAABBwAAAH+"
  },
  "main_window_geometry": {
    "__class__": "bytearray",
    "__value__": "AdnQywADAAAAAAMmAAAAKAAABjMAAAN3AAADKAAAACoAAAYxAAADdQAAAAAAAAAABkAAAAMoAAAAKgAABjEAAAN1"
  },
  "main_window_state": {
    "__class__": "bytearray",
    "__value__": "AAAA/wAAAAD9AAAABAAAAAAAAAFpAAACvvwCAAAABfsAAAAkAGYAaQBsAGUAcwAtAGIAcgBvAHcAcwBlAHIALQBkAG8AYwBrAQAAABkAAAK+AAAAXAD////7AAAAHgB0AG8AYwAtAHYAaQBlAHcAZQByAC0AZABvAGMAawAAAAAA/////wAAAFwA////+wAAACAAdABlAHgAdAAtAHMAZQBhAHIAYwBoAC0AZABvAGMAawAAAAAA/////wAAAIUA////+wAAACAAYwBoAGUAYwBrAHAAbwBpAG4AdABzAC0AZABvAGMAawAAAAAZAAADGgAAAJAA////+wAAACYAcwBhAHYAZQBkAC0AcwBlAGEAcgBjAGgAZQBzAC0AZABvAGMAawAAAAAA/////wAAAjUA////AAAAAQAAAEEAAAK+/AIAAAAC+wAAABgAcAByAGUAdgBpAGUAdwAtAGQAbwBjAGsBAAAAGQAAAr4AAABXAP////sAAAAaAGwAaQB2AGUALQBjAHMAcwAtAGQAbwBjAGsAAAAAAP////8AAABcAP///wAAAAIAAAAAAAAAAPwBAAAAAfsAAAAeAGMAaABlAGMAawAtAGIAbwBvAGsALQBkAG8AYwBrAAAAAAD/////AAAAkAD///8AAAADAAAAAAAAAAD8AQAAAAH7AAAAHABpAG4AcwBwAGUAYwB0AG8AcgAtAGQAbwBjAGsAAAAAAP////8AAAA3AP///wAAAooAAAK+AAAABAAAAAQAAAAIAAAACPwAAAABAAAAAAAAAAMAAAAUAGcAbABvAGIAYQBsAC0AYgBhAHIDAAAAAP////8AAAAAAAAAAAAAABYAcABsAHUAZwBpAG4AcwAtAGIAYQByAwAAAR7/////AAAAAAAAAAAAAAASAHQAbwBvAGwAcwAtAGIAYQByAwAAAS8AAAHrAAAAAAAAAAA="
  },
  "preview_standard_font_family": null,
  "recent-books": [
    "/home/nathias/Library/Aleister Crowley/The Book of Lies (829)/The Book of Lies - Aleister Crowley.epub",
    "/home/nathias/Library/Tolkien, J.R.R_/The Lord of the Rings (2319)/The Lord of the Rings - Tolkien, J.R.R_.epub",
    "/home/nathias/Library/Unknown/Sense and Reference -- Frege, Gottlob -- 0 -- 7d7b9d6d09e96c8a0df6833e83c709fd -- Anna's Archiv (3335)/Sense and Reference -- Frege, Gottlob -- 0 - Unknown.epub",
    "/home/nathias/Library/Matija Potocnik Pribosic/Hypocrisis (1760)/Hypocrisis - Matija Potocnik Pribosic.epub",
    "/home/nathias/Library/Dan Simmons/Endymion (3228)/Endymion - Dan Simmons.epub",
    "/home/nathias/Library/Dan Simmons/Endymion (3226)/Endymion - Dan Simmons.epub",
    "/home/nathias/Library/G. W. Leibniz/New Essays on Human Understanding (1642)/New Essays on Human Understanding - G. W. Leibniz.epub",
    "/home/nathias/Library/Weber, David/On Basilisk Station (Honor Harrington) (3222)/On Basilisk Station (Honor Harrington) - Weber, David.epub",
    "/home/nathias/Library/Gene Wolfe/Shadow & Claw (3028)/Shadow & Claw - Gene Wolfe.epub",
    "/home/nathias/Library/McKenzie Wark/A Hacker Manifesto (2396)/A Hacker Manifesto - McKenzie Wark.epub"
  ],
  "reports-ui-state": {
    "all-files-table": {
      "__class__": "bytearray",
      "__value__": "AAAA/wAAAAAAAAABAAAAAAAAAAEBAAAAAAAAAAAAAAAAAAAAAAAAAfQAAAAFAQEBAAAAAAAAAAAAAAAAAGT/////AAAAhAAAAAAAAAAFAAAAZAAAAAEAAAAAAAAAZAAAAAEAAAAAAAAAZAAAAAEAAAAAAAAAZAAAAAEAAAAAAAAAZAAAAAEAAAAAAAAD6AAAAAAAAAAAAA=="
    },
    "chars-table": {
      "__class__": "bytearray",
      "__value__": "AAAA/wAAAAAAAAABAAAAAAAAAAABAAAAAAAAAAAAAAAAAAAAAAAAAZAAAAAEAQEBAAAAAAAAAAAAAAAAAGT/////AAAAhAAAAAAAAAAEAAAAZAAAAAEAAAAAAAAAZAAAAAEAAAAAAAAAZAAAAAEAAAAAAAAAZAAAAAEAAAAAAAAD6AAAAAAAAAAAAA=="
    },
    "classes-sort-ascending": true,
    "classes-sort-on-counts": true,
    "css-sort-ascending": true,
    "css-sort-on-counts": true,
    "image-files-table": {
      "__class__": "bytearray",
      "__value__": "AAAA/wAAAAAAAAABAAAAAAAAAAABAAAAAAAAAAAAAAAAAAAAAAAAAZAAAAAEAQEBAAAAAAAAAAAAAAAAAGT/////AAAAhAAAAAAAAAAEAAAAZAAAAAEAAAAAAAAAZAAAAAEAAAAAAAAAZAAAAAEAAAAAAAAAZAAAAAEAAAAAAAAD6AAAAAAAAAAAAA=="
    },
    "links-table": {
      "__class__": "bytearray",
      "__value__": "AAAA/wAAAAAAAAABAAAAAAAAAAEBAAAAAAAAAAAAAAAAAAAAAAAAAlgAAAAGAQEBAAAAAAAAAAAAAAAAAGT/////AAAAhAAAAAAAAAAGAAAAZAAAAAEAAAAAAAAAZAAAAAEAAAAAAAAAZAAAAAEAAAAAAAAAZAAAAAEAAAAAAAAAZAAAAAEAAAAAAAAAZAAAAAEAAAAAAAAD6AAAAAAAAAAAAA=="
    },
    "links-view-splitter": {
      "__class__": "bytearray",
      "__value__": "AAAA/wAAAAEAAAAC//////////8B/////wEAAAACAA=="
    },
    "report-page": -1,
    "splitter-state": {
      "__class__": "bytearray",
      "__value__": "AAAA/wAAAAEAAAACAAABAAABW6MA/////wEAAAABAA=="
    },
    "words-table": {
      "__class__": "bytearray",
      "__value__": "AAAA/wAAAAAAAAABAAAAAAAAAAABAAAAAAAAAAAAAAAAAAAAAAAAASwAAAADAQEBAAAAAAAAAAAAAAAAAGT/////AAAAhAAAAAAAAAADAAAAZAAAAAEAAAAAAAAAZAAAAAEAAAAAAAAAZAAAAAEAAAAAAAAD6AAAAAAAAAAAAA=="
    }
  },
  "saved_seaches_state": {
    "direction": "down",
    "where": "current",
    "wrap": true
  },
  "search-panel-visible": false,
  "text_search_widget_state": {
    "case_sensitive": false,
    "dot_all": true,
    "mode": "normal",
    "where": "current"
  }
}